leonadormida/__init__.py
leonadormida/main.py
leonadormida-0.1.0.dist-info/WHEEL
leonadormida-0.1.0.dist-info/METADATA
leonadormida-0.1.0.dist-info/RECORD
