Metadata-Version: 2.1
Name: leonadormida
Version: 0.1.0
Summary: 
Author: Danilo
Author-email: drleon416@gmail.com
Requires-Python: >=3.10,<4.0
Classifier: Programming Language :: Python :: 3
Classifier: Programming Language :: Python :: 3.10
Requires-Dist: numpy (>=1.23.0,<2.0.0)
